vxfreeswitch/__init__.py
vxfreeswitch/client.py
vxfreeswitch/originate.py
vxfreeswitch/voice.py
vxfreeswitch/tests/__init__.py
vxfreeswitch/tests/helpers.py
vxfreeswitch/tests/test_client.py
vxfreeswitch/tests/test_originate.py
vxfreeswitch/tests/test_voice.py
vxfreeswitch-0.1.18.dist-info/DESCRIPTION.rst
vxfreeswitch-0.1.18.dist-info/METADATA
vxfreeswitch-0.1.18.dist-info/RECORD
vxfreeswitch-0.1.18.dist-info/WHEEL
vxfreeswitch-0.1.18.dist-info/metadata.json
vxfreeswitch-0.1.18.dist-info/top_level.txt
