Metadata-Version: 2.0
Name: vxfreeswitch
Version: 0.1.18
Summary: A Freeswitch eventsocket transport for Vumi.
Home-page: http://github.com/praekelt/vumi-freeswitch-esl
Author: Praekelt Foundation
Author-email: dev@praekeltfoundation.org
License: BSD
Platform: UNKNOWN
Classifier: Development Status :: 4 - Beta
Classifier: Intended Audience :: Developers
Classifier: License :: OSI Approved :: BSD License
Classifier: Operating System :: POSIX
Classifier: Programming Language :: Python
Classifier: Topic :: Software Development :: Libraries :: Python Modules
Classifier: Topic :: System :: Networking
Requires-Dist: vumi
Requires-Dist: confmodel (>=0.2.0)
Requires-Dist: Twisted (>=13.1.0)
Requires-Dist: eventsocket (==0.1.5)
